Metadata-Version: 1.0
Name: txWS-Upgrade
Version: 0.9.1.post4
Summary: Twisted WebSockets wrapper
Home-page: http://github.com/MostAwesomeDude/txWS
Author: Corbin Simpson
Author-email: simpsoco@osuosl.org
License: MIT/X11
Platform: UNKNOWN
